eha_jsonpath/__init__.py
eha_jsonpath/ext_functions.py
eha_jsonpath-0.6.0.dist-info/LICENSE
eha_jsonpath-0.6.0.dist-info/METADATA
eha_jsonpath-0.6.0.dist-info/WHEEL
eha_jsonpath-0.6.0.dist-info/top_level.txt
eha_jsonpath-0.6.0.dist-info/RECORD
