Metadata-Version: 2.1
Name: eha-jsonpath
Version: 0.6.0
Summary: jsonpath_ng with extended functionality
Home-page: https://github.com/eHealthAfrica/jsonpath-extensions/
Author: eHealth Africa
Author-email: aether@ehealthafrica.org
License: Apache2 License
Platform: UNKNOWN
Requires-Dist: jsonpath-ng
